Workbook

Sheet 充放测算
A1: 储能每日充放测算
A2: 充电支出 | L2: 放电收入 | O2: 其他 | Q2: 收益
A3: 充电均价 (元/MWh) | B3: 充电电量(MWh) | C3: 交易充电 费用(元) | D3: 优发优购(元) | E3: 上网线损(元) | F3: 输配电费(元) | G3: 政府基金(元) | H3: 系统运行(元) | I3: 容量分摊(元) | J3: 容量分摊 系数 | K3: 充电总 费用(元) | L3: 放电均价 (元/MWh) | M3: 放电电量(MWh) | N3: 放电电费 (元) | O3: 综合效率 | P3: 充放价差 (元/MWh) | Q3: 现货价差 收入 | R3: 调频收入 | S3: 其他费用（过网费、容量分摊等） | T3: 总收入
A4: =充电日清算费用!AC29 -> 363.71114 | B4: =-充电日清算费用!AB29 -> -215.177 | C4: =-充电日清算费用!AD29 -> -78262.272 | D4: =$B$4*I12 -> -753.1195 | E4: =$B$4*I13 -> -710.0841 | F4: =B4*(1-O4)*I8 -> -4899.5908 | G4: =B4*(1-O4)*I9 -> -693.65338 | H4: =$B$4*I14 -> 624.0133 | I4: =B4*J4*70.5 -> -10263.325 | J4: 0.676555 | K4: =C4+D4+E4+F4+G4+H4+I4 -> -94958.032 | L4: =N4/M4 -> 416.61654 | M4: =放电日清算费用!AO101 -> 189.645 | N4: =放电日清算费用!Q101 -> 79009.244 | O4: =-M4/B4 -> 0.8813442 | P4: =L4-A4 -> 52.905398 | Q4: =N4+C4 -> 746.97131 | R4: =放电日清算费用!AJ101 -> 20981.27 | S4: =SUM(D4:I4) -> -16695.759 | T4: =Q4+R4+S4 -> 5032.482
A6: 说明 | B6: 根据预测电价，输入充电均价，放电均价。根据充电时段计算出对于的容量分摊系数，计入容量分摊。 | K6: =K3 -> 充电总 费用(元)
A7: 1 | B7: 充电均价（元 / MWh）输入限制：-100 至 800； | K7: =C3 -> 交易充电 费用(元)
A8: 2 | B8: 输配电价（元 / MWh）设置：收取损耗部分输配电价； | I8: 191.9 | J8: 政府核定 | K8: =D3 -> 优发优购(元)
A9: 3 | B9: 政府基金（元 /M Wh）设置：收取损耗部分输配电价； | I9: 27.168 | J9: 政府核定 | K9: =E3 -> 上网线损(元)
A10: 4 | B10: 综合效率设置：60% 至 100%； | K10: =F3 -> 输配电费(元)
A11: 5 | B11: 放电均价（元 / MWh）输入限制：100 至 1500； | K11: =G3 -> 政府基金(元)
A12: 6 | B12: 优发优购曲线匹配偏差标准：暂以上月替代； | I12: 3.5 | J12: 上月均值 | K12: =H3 -> 系统运行(元)
A13: 7 | B13: 上网环节线损费用； | I13: 3.3 | J13: 上月均值 | K13: =I3 -> 容量分摊(元)
A14: 8 | B14: 系统运行费用； | I14: -2.9 | J14: 上月均值
A15: 9 | B15: 容量分摊：按季度分为4种类型，详见附表；
A16: 10 | B16: 根据选择的充电时段，计算容量分摊系数。

Sheet 充电日清算费用
F1: 2026年5月25日日清算临时结果单（售电侧）
A2: 德州润津储能科技有限公司(用电): | AD2: 单位：兆瓦时、元/兆瓦时、元
A3: 时段 | C3: 省内实时市场结算 | F3: 省内日前市场结算 | J3: 省内中长期结算 | N3: 跨省跨区直接交易结算 | V3: 运行成本类费用 | X3: 市场偏差类费用 | Y3: 辅助服务费用 | AA3: 虚拟电厂调节 | AB3: 总计
C4: 实时用电量 | D4: 实时市场电价 | E4: 实时电能量电费 | F4: 日前出清电量 | G4: 日前市场出清电价 | H4: 实时市场统一结算点电价 | I4: 日前电能量电费 | J4: 中长期合约电量 | K4: 中长期合约电价 | L4: 中长期结算参考点现货市场电价 | M4: 中长期合约电费 | N4: 银东双边电量 | O4: 银东双边价格 | P4: 实时市场统一结算点电价 | Q4: 银东双边电费 | R4: 银东竞价电量 | S4: 银东竞价价格 | T4: 实时市场统一结算点电价 | U4: 银东竞价电费 | V4: 运行成本补偿费用 | W4: 运行成本补偿费用分摊 | X4: 市场超额收益回收返还 | Y4: 调频辅助服务费用分摊 | Z4: 爬坡辅助服务费用分摊 | AA4: 削峰调节电量电费分摊 | AB4: 总结算电量 | AC4: 总结算均价 | AD4: 总结算费用
A5: 01:00 | C5: 0.352 | D5: 383.22 | E5: 134.89344 | F5: 0 | G5: 0 | H5: 383.22 | I5: 0 | J5: 0 | K5: 0 | L5: 0 | M5: 0 | N5: 0 | O5: 0 | P5: 383.22 | Q5: 0 | R5: 0 | S5: 0 | T5: 383.22 | U5: 0 | V5: 0 | W5: 0 | X5: 0 | Y5: 0 | Z5: 0 | AA5: 0 | AB5: 0.352 | AC5: 383.22 | AD5: 134.89344
A6: 02:00 | C6: 0.264 | D6: 364.202 | E6: 96.149328 | F6: 0 | G6: 0 | H6: 364.202 | I6: 0 | J6: 0 | K6: 0 | L6: 0 | M6: 0 | N6: 0 | O6: 0 | P6: 364.202 | Q6: 0 | R6: 0 | S6: 0 | T6: 364.202 | U6: 0 | V6: 0 | W6: 0 | X6: 0 | Y6: 0 | Z6: 0 | AA6: 0 | AB6: 0.264 | AC6: 364.202 | AD6: 96.149328
A7: 03:00 | C7: 23.605 | D7: 348.481 | E7: 8225.894 | F7: 0 | G7: 0 | H7: 348.481 | I7: 0 | J7: 0 | K7: 0 | L7: 0 | M7: 0 | N7: 0 | O7: 0 | P7: 348.481 | Q7: 0 | R7: 0 | S7: 0 | T7: 348.481 | U7: 0 | V7: 0 | W7: 0 | X7: 0 | Y7: 0 | Z7: 0 | AA7: 0 | AB7: 23.605 | AC7: 348.481 | AD7: 8225.894
A8: 04:00 | C8: 37.609 | D8: 342.467 | E8: 12879.841 | F8: 0 | G8: 0 | H8: 342.467 | I8: 0 | J8: 0 | K8: 0 | L8: 0 | M8: 0 | N8: 0 | O8: 0 | P8: 342.467 | Q8: 0 | R8: 0 | S8: 0 | T8: 342.467 | U8: 0 | V8: 0 | W8: 0 | X8: 0 | Y8: 0 | Z8: 0 | AA8: 0 | AB8: 37.609 | AC8: 342.467 | AD8: 12879.841
A9: 05:00 | C9: 24.045 | D9: 354.262 | E9: 8518.2298 | F9: 0 | G9: 0 | H9: 354.262 | I9: 0 | J9: 0 | K9: 0 | L9: 0 | M9: 0 | N9: 0 | O9: 0 | P9: 354.262 | Q9: 0 | R9: 0 | S9: 0 | T9: 354.262 | U9: 0 | V9: 0 | W9: 0 | X9: 0 | Y9: 0 | Z9: 0 | AA9: 0 | AB9: 24.045 | AC9: 354.262 | AD9: 8518.2298
A10: 06:00 | C10: 0.352 | D10: 360.66 | E10: 126.95232 | F10: 0 | G10: 0 | H10: 360.66 | I10: 0 | J10: 0 | K10: 0 | L10: 0 | M10: 0 | N10: 0 | O10: 0 | P10: 360.66 | Q10: 0 | R10: 0 | S10: 0 | T10: 360.66 | U10: 0 | V10: 0 | W10: 0 | X10: 0 | Y10: 0 | Z10: 0 | AA10: 0 | AB10: 0.352 | AC10: 360.66 | AD10: 126.95232
A11: 07:00 | C11: 36.2 | D11: 358.633 | E11: 12982.515 | F11: 0 | G11: 0 | H11: 358.633 | I11: 0 | J11: 0 | K11: 0 | L11: 0 | M11: 0 | N11: 0 | O11: 0 | P11: 358.633 | Q11: 0 | R11: 0 | S11: 0 | T11: 358.633 | U11: 0 | V11: 0 | W11: 0 | X11: 0 | Y11: 0 | Z11: 0 | AA11: 0 | AB11: 36.2 | AC11: 358.633 | AD11: 12982.515
A12: 08:00 | C12: 49.94 | D12: 332.411 | E12: 16600.605 | F12: 0 | G12: 0 | H12: 332.411 | I12: 0 | J12: 0 | K12: 0 | L12: 0 | M12: 0 | N12: 0 | O12: 0 | P12: 332.411 | Q12: 0 | R12: 0 | S12: 0 | T12: 332.411 | U12: 0 | V12: 0 | W12: 0 | X12: 0 | Y12: 0 | Z12: 0 | AA12: 0 | AB12: 49.94 | AC12: 332.411 | AD12: 16600.605
A13: 09:00 | C13: 0.44 | D13: 357.5 | E13: 157.3 | F13: 0 | G13: 0 | H13: 357.5 | I13: 0 | J13: 0 | K13: 0 | L13: 0 | M13: 0 | N13: 0 | O13: 0 | P13: 357.5 | Q13: 0 | R13: 0 | S13: 0 | T13: 357.5 | U13: 0 | V13: 0 | W13: 0 | X13: 0 | Y13: 0 | Z13: 0 | AA13: 0 | AB13: 0.44 | AC13: 357.5 | AD13: 157.3
A14: 10:00 | C14: 11.45 | D14: 366.574 | E14: 4197.2723 | F14: 0 | G14: 0 | H14: 366.574 | I14: 0 | J14: 0 | K14: 0 | L14: 0 | M14: 0 | N14: 0 | O14: 0 | P14: 366.574 | Q14: 0 | R14: 0 | S14: 0 | T14: 366.574 | U14: 0 | V14: 0 | W14: 0 | X14: 0 | Y14: 0 | Z14: 0 | AA14: 0 | AB14: 11.45 | AC14: 366.574 | AD14: 4197.2723
A15: 11:00 | C15: 0 | D15: 413.906 | E15: 0 | F15: 0 | G15: 0 | H15: 413.906 | I15: 0 | J15: 0 | K15: 0 | L15: 0 | M15: 0 | N15: 0 | O15: 0 | P15: 413.906 | Q15: 0 | R15: 0 | S15: 0 | T15: 413.906 | U15: 0 | V15: 0 | W15: 0 | X15: 0 | Y15: 0 | Z15: 0 | AA15: 0 | AB15: 0 | AC15: - | AD15: 0
A16: 12:00 | C16: 0.001 | D16: 421.75 | E16: 0.42175 | F16: 0 | G16: 0 | H16: 421.75 | I16: 0 | J16: 0 | K16: 0 | L16: 0 | M16: 0 | N16: 0 | O16: 0 | P16: 421.75 | Q16: 0 | R16: 0 | S16: 0 | T16: 421.75 | U16: 0 | V16: 0 | W16: 0 | X16: 0 | Y16: 0 | Z16: 0 | AA16: 0 | AB16: 0.001 | AC16: 421.75 | AD16: 0.42175
A17: 13:00 | C17: 18.937 | D17: 431.9 | E17: 8178.8903 | F17: 0 | G17: 0 | H17: 431.9 | I17: 0 | J17: 0 | K17: 0 | L17: 0 | M17: 0 | N17: 0 | O17: 0 | P17: 431.9 | Q17: 0 | R17: 0 | S17: 0 | T17: 431.9 | U17: 0 | V17: 0 | W17: 0 | X17: 0 | Y17: 0 | Z17: 0 | AA17: 0.04 | AB17: 18.937 | AC17: 431.90211 | AD17: 8178.9303
A18: 14:00 | C18: 8.81 | D18: 441 | E18: 3885.21 | F18: 0 | G18: 0 | H18: 441 | I18: 0 | J18: 0 | K18: 0 | L18: 0 | M18: 0 | N18: 0 | O18: 0 | P18: 441 | Q18: 0 | R18: 0 | S18: 0 | T18: 441 | U18: 0 | V18: 0 | W18: 0 | X18: 0 | Y18: 0 | Z18: 0 | AA18: 0.02 | AB18: 8.81 | AC18: 441.00227 | AD18: 3885.23
A19: 15:00 | C19: 0.353 | D19: 447.375 | E19: 157.92337 | F19: 0 | G19: 0 | H19: 447.375 | I19: 0 | J19: 0 | K19: 0 | L19: 0 | M19: 0 | N19: 0 | O19: 0 | P19: 447.375 | Q19: 0 | R19: 0 | S19: 0 | T19: 447.375 | U19: 0 | V19: 0 | W19: 0 | X19: 0 | Y19: 0 | Z19: 0 | AA19: 0 | AB19: 0.353 | AC19: 447.375 | AD19: 157.92337
A20: 16:00 | C20: 0.353 | D20: 444.05 | E20: 156.74965 | F20: 0 | G20: 0 | H20: 444.05 | I20: 0 | J20: 0 | K20: 0 | L20: 0 | M20: 0 | N20: 0 | O20: 0 | P20: 444.05 | Q20: 0 | R20: 0 | S20: 0 | T20: 444.05 | U20: 0 | V20: 0 | W20: 0 | X20: 0 | Y20: 0 | Z20: 0 | AA20: 0 | AB20: 0.353 | AC20: 444.05 | AD20: 156.74965
A21: 17:00 | C21: 0.353 | D21: 428.003 | E21: 151.08506 | F21: 0 | G21: 0 | H21: 428.003 | I21: 0 | J21: 0 | K21: 0 | L21: 0 | M21: 0 | N21: 0 | O21: 0 | P21: 428.003 | Q21: 0 | R21: 0 | S21: 0 | T21: 428.003 | U21: 0 | V21: 0 | W21: 0 | X21: 0 | Y21: 0 | Z21: 0 | AA21: 0 | AB21: 0.353 | AC21: 428.003 | AD21: 151.08506
A22: 18:00 | C22: 0.265 | D22: 393.503 | E22: 104.27829 | F22: 0 | G22: 0 | H22: 393.503 | I22: 0 | J22: 0 | K22: 0 | L22: 0 | M22: 0 | N22: 0 | O22: 0 | P22: 393.503 | Q22: 0 | R22: 0 | S22: 0 | T22: 393.503 | U22: 0 | V22: 0 | W22: 0 | X22: 0 | Y22: 0 | Z22: 0 | AA22: 0 | AB22: 0.265 | AC22: 393.503 | AD22: 104.27829
A23: 19:00 | C23: 0.352 | D23: 378.417 | E23: 133.20278 | F23: 0 | G23: 0 | H23: 378.417 | I23: 0 | J23: 0 | K23: 0 | L23: 0 | M23: 0 | N23: 0 | O23: 0 | P23: 378.417 | Q23: 0 | R23: 0 | S23: 0 | T23: 378.417 | U23: 0 | V23: 0 | W23: 0 | X23: 0 | Y23: 0 | Z23: 0 | AA23: 0.01 | AB23: 0.352 | AC23: 378.44541 | AD23: 133.21278
A24: 20:00 | C24: 0.264 | D24: 382.26 | E24: 100.91664 | F24: 0 | G24: 0 | H24: 382.26 | I24: 0 | J24: 0 | K24: 0 | L24: 0 | M24: 0 | N24: 0 | O24: 0 | P24: 382.26 | Q24: 0 | R24: 0 | S24: 0 | T24: 382.26 | U24: 0 | V24: 0 | W24: 0 | X24: 0 | Y24: 0 | Z24: 0 | AA24: 0.01 | AB24: 0.264 | AC24: 382.29788 | AD24: 100.92664
A25: 21:00 | C25: 0.264 | D25: 373.642 | E25: 98.641488 | F25: 0 | G25: 0 | H25: 373.642 | I25: 0 | J25: 0 | K25: 0 | L25: 0 | M25: 0 | N25: 0 | O25: 0 | P25: 373.642 | Q25: 0 | R25: 0 | S25: 0 | T25: 373.642 | U25: 0 | V25: 0 | W25: 0 | X25: 0 | Y25: 0 | Z25: 0 | AA25: 0.01 | AB25: 0.264 | AC25: 373.67988 | AD25: 98.651488
A26: 22:00 | C26: 0.352 | D26: 356.924 | E26: 125.63725 | F26: 0 | G26: 0 | H26: 356.924 | I26: 0 | J26: 0 | K26: 0 | L26: 0 | M26: 0 | N26: 0 | O26: 0 | P26: 356.924 | Q26: 0 | R26: 0 | S26: 0 | T26: 356.924 | U26: 0 | V26: 0 | W26: 0 | X26: 0 | Y26: 0 | Z26: 0 | AA26: 0.01 | AB26: 0.352 | AC26: 356.95241 | AD26: 125.64725
A27: 23:00 | C27: 0.264 | D27: 345.213 | E27: 91.136232 | F27: 0 | G27: 0 | H27: 345.213 | I27: 0 | J27: 0 | K27: 0 | L27: 0 | M27: 0 | N27: 0 | O27: 0 | P27: 345.213 | Q27: 0 | R27: 0 | S27: 0 | T27: 345.213 | U27: 0 | V27: 0 | W27: 0 | X27: 0 | Y27: 0 | Z27: 0 | AA27: 0 | AB27: 0.264 | AC27: 345.213 | AD27: 91.136232
A28: 24:00 | C28: 0.352 | D28: 319.31 | E28: 112.39712 | F28: 0 | G28: 0 | H28: 319.31 | I28: 0 | J28: 0 | K28: 0 | L28: 0 | M28: 0 | N28: 0 | O28: 0 | P28: 319.31 | Q28: 0 | R28: 0 | S28: 0 | T28: 319.31 | U28: 0 | V28: 0 | W28: 0 | X28: 0 | Y28: 0 | Z28: 0 | AA28: 0 | AB28: 0.352 | AC28: 319.31 | AD28: 112.39712
A29: 合计 | C29: 215.177 | D29: 358.84942 | E29: 77216.142 | F29: 0 | G29: - | H29: - | I29: 0 | J29: 0 | K29: - | L29: - | M29: 0 | N29: 0 | O29: - | P29: - | Q29: 0 | R29: 0 | S29: - | T29: - | U29: 0 | V29: 0 | W29: 680.52 | X29: 0 | Y29: 365.51 | Z29: 0 | AA29: 0.1 | AB29: 215.177 | AC29: 363.71114 | AD29: 78262.272

Sheet 放电日清算费用
A1: 2026年5月25日日清算临时结果单（发电侧）
A2: 德州润津储能科技有限公司(发电): | AP2: 单位：兆瓦时、元/兆瓦时、元
A3: 时段 | B3: 跨省跨区结算 | K3: 非市场结算 | N3: 调试期结算 | O3: 省内实时市场结算 | R3: 省内日前市场结算 | V3: 省内中长期结算 | Z3: 运行成本补偿及分摊 | AG3: 供热考核及返还 | AI3: 市场超额收益回收 | AJ3: 调频辅助服务 | AL3: 爬坡辅助服务 | AO3: 总结算电量及费用
B4: 省间中长期结算电量 | C4: 省间中长期结算价格 | D4: 省间中长期结算电费 | E4: 省间日前结算电量 | F4: 省间日前结算价格 | G4: 省间日前结算电费 | H4: 省间应急外送结算电量 | I4: 省间应急外送结算价格 | J4: 省间应急外送结算电费 | K4: 非市场结算电量 | L4: 非市场结算价格 | M4: 非市场电能量电费 | N4: 调试期结算电量 | O4: 实际上网电量 | P4: 实时市场节点电价 | Q4: 实时电能量电费 | R4: 日前出清电量 | S4: 日前市场出清电价 | T4: 实时市场统一结算点电价 | U4: 日前电能量电费 | V4: 中长期合约电量 | W4: 中长期合约固定价格 | X4: 中长期结算参考点现货市场电价 | Y4: 中长期合约电费 | Z4: 启动成本 | AA4: 启动方式（0冷,1温,2热） | AB4: 空载费用 | AC4: 电能量成本 | AD4: 总成本 | AE4: 运行成本补偿费用 | AF4: 运行成本分摊费用 | AG4: 供热考核费用 | AH4: 供热返还费用 | AI4: 市场超额收益回收 | AJ4: 调频辅助服务补偿费用 | AK4: 调频辅助服务分摊费用 | AL4: 爬坡辅助服务补偿费用 | AM4: 爬坡辅助服务考核费用 | AN4: 爬坡辅助服务分摊费用 | AO4: 总结算电量 | AP4: 总结算费用
A5: 00:15 | B5: 0 | C5: 0 | D5: 0 | E5: 0 | F5: 0 | G5: 0 | K5: 0 | L5: 0 | M5: 0 | N5: 0 | O5: 0 | P5: 397.88 | Q5: 0 | R5: 0 | S5: 0 | T5: 397.88 | U5: 0 | V5: 0 | W5: 0 | X5: 0 | Y5: 0 | AD5: 0 | AE5: 0 | AF5: 0 | AG5: 0 | AH5: 0 | AI5: 0 | AJ5: 0 | AK5: 0 | AL5: 0 | AM5: 0 | AN5: 0 | AO5: 0 | AP5: 0
A6: 00:30 | B6: 0 | C6: 0 | D6: 0 | E6: 0 | F6: 0 | G6: 0 | K6: 0 | L6: 0 | M6: 0 | N6: 0 | O6: 0 | P6: 383 | Q6: 0 | R6: 0 | S6: 0 | T6: 383 | U6: 0 | V6: 0 | W6: 0 | X6: 0 | Y6: 0 | AD6: 0 | AE6: 0 | AF6: 0 | AG6: 0 | AH6: 0 | AI6: 0 | AJ6: 0 | AK6: 0 | AL6: 0 | AM6: 0 | AN6: 0 | AO6: 0 | AP6: 0
A7: 00:45 | B7: 0 | C7: 0 | D7: 0 | E7: 0 | F7: 0 | G7: 0 | K7: 0 | L7: 0 | M7: 0 | N7: 0 | O7: 0 | P7: 378 | Q7: 0 | R7: 0 | S7: 0 | T7: 378 | U7: 0 | V7: 0 | W7: 0 | X7: 0 | Y7: 0 | AD7: 0 | AE7: 0 | AF7: 0 | AG7: 0 | AH7: 0 | AI7: 0 | AJ7: 0 | AK7: 0 | AL7: 0 | AM7: 0 | AN7: 0 | AO7: 0 | AP7: 0
A8: 01:00 | B8: 0 | C8: 0 | D8: 0 | E8: 0 | F8: 0 | G8: 0 | K8: 0 | L8: 0 | M8: 0 | N8: 0 | O8: 0 | P8: 374 | Q8: 0 | R8: 0 | S8: 0 | T8: 374 | U8: 0 | V8: 0 | W8: 0 | X8: 0 | Y8: 0 | AD8: 0 | AE8: 0 | AF8: 0 | AG8: 0 | AH8: 0 | AI8: 0 | AJ8: 0 | AK8: 0 | AL8: 0 | AM8: 0 | AN8: 0 | AO8: 0 | AP8: 0
A9: 01:15 | B9: 0 | C9: 0 | D9: 0 | E9: 0 | F9: 0 | G9: 0 | K9: 0 | L9: 0 | M9: 0 | N9: 0 | O9: 0 | P9: 371.212 | Q9: 0 | R9: 0 | S9: 0 | T9: 371.21 | U9: 0 | V9: 0 | W9: 0 | X9: 0 | Y9: 0 | AD9: 0 | AE9: 0 | AF9: 0 | AG9: 0 | AH9: 0 | AI9: 0 | AJ9: 0 | AK9: 0 | AL9: 0 | AM9: 0 | AN9: 0 | AO9: 0 | AP9: 0
A10: 01:30 | B10: 0 | C10: 0 | D10: 0 | E10: 0 | F10: 0 | G10: 0 | K10: 0 | L10: 0 | M10: 0 | N10: 0 | O10: 0 | P10: 368.216 | Q10: 0 | R10: 0 | S10: 0 | T10: 368.22 | U10: 0 | V10: 0 | W10: 0 | X10: 0 | Y10: 0 | AD10: 0 | AE10: 0 | AF10: 0 | AG10: 0 | AH10: 0 | AI10: 0 | AJ10: 0 | AK10: 0 | AL10: 0 | AM10: 0 | AN10: 0 | AO10: 0 | AP10: 0
A11: 01:45 | B11: 0 | C11: 0 | D11: 0 | E11: 0 | F11: 0 | G11: 0 | K11: 0 | L11: 0 | M11: 0 | N11: 0 | O11: 0 | P11: 360 | Q11: 0 | R11: 0 | S11: 0 | T11: 360 | U11: 0 | V11: 0 | W11: 0 | X11: 0 | Y11: 0 | AD11: 0 | AE11: 0 | AF11: 0 | AG11: 0 | AH11: 0 | AI11: 0 | AJ11: 0 | AK11: 0 | AL11: 0 | AM11: 0 | AN11: 0 | AO11: 0 | AP11: 0
A12: 02:00 | B12: 0 | C12: 0 | D12: 0 | E12: 0 | F12: 0 | G12: 0 | K12: 0 | L12: 0 | M12: 0 | N12: 0 | O12: 0 | P12: 357.378 | Q12: 0 | R12: 0 | S12: 0 | T12: 357.38 | U12: 0 | V12: 0 | W12: 0 | X12: 0 | Y12: 0 | AD12: 0 | AE12: 0 | AF12: 0 | AG12: 0 | AH12: 0 | AI12: 0 | AJ12: 0 | AK12: 0 | AL12: 0 | AM12: 0 | AN12: 0 | AO12: 0 | AP12: 0
A13: 02:15 | B13: 0 | C13: 0 | D13: 0 | E13: 0 | F13: 0 | G13: 0 | K13: 0 | L13: 0 | M13: 0 | N13: 0 | O13: 0 | P13: 354 | Q13: 0 | R13: 0 | S13: 0 | T13: 354 | U13: 0 | V13: 0 | W13: 0 | X13: 0 | Y13: 0 | AD13: 0 | AE13: 0 | AF13: 0 | AG13: 0 | AH13: 0 | AI13: 0 | AJ13: 0 | AK13: 0 | AL13: 0 | AM13: 0 | AN13: 0 | AO13: 0 | AP13: 0
A14: 02:30 | B14: 0 | C14: 0 | D14: 0 | E14: 0 | F14: 0 | G14: 0 | K14: 0 | L14: 0 | M14: 0 | N14: 0 | O14: 0 | P14: 350 | Q14: 0 | R14: 0 | S14: 0 | T14: 350 | U14: 0 | V14: 0 | W14: 0 | X14: 0 | Y14: 0 | AD14: 0 | AE14: 0 | AF14: 0 | AG14: 0 | AH14: 0 | AI14: 0 | AJ14: 0 | AK14: 0 | AL14: 0 | AM14: 0 | AN14: 0 | AO14: 0 | AP14: 0
A15: 02:45 | B15: 0 | C15: 0 | D15: 0 | E15: 0 | F15: 0 | G15: 0 | K15: 0 | L15: 0 | M15: 0 | N15: 0 | O15: 0 | P15: 344 | Q15: 0 | R15: 0 | S15: 0 | T15: 344 | U15: 0 | V15: 0 | W15: 0 | X15: 0 | Y15: 0 | AD15: 0 | AE15: 0 | AF15: 0 | AG15: 0 | AH15: 0 | AI15: 0 | AJ15: 0 | AK15: 0 | AL15: 0 | AM15: 0 | AN15: 0 | AO15: 0 | AP15: 0
A16: 03:00 | B16: 0 | C16: 0 | D16: 0 | E16: 0 | F16: 0 | G16: 0 | K16: 0 | L16: 0 | M16: 0 | N16: 0 | O16: 0 | P16: 345.923 | Q16: 0 | R16: 0 | S16: 0 | T16: 345.92 | U16: 0 | V16: 0 | W16: 0 | X16: 0 | Y16: 0 | AD16: 0 | AE16: 0 | AF16: 0 | AG16: 0 | AH16: 0 | AI16: 0 | AJ16: 0 | AK16: 0 | AL16: 0 | AM16: 0 | AN16: 0 | AO16: 0 | AP16: 0
... A100: 24:00 | B100: 0 | C100: 0 | D100: 0 | E100: 0 | F100: 0 | G100: 0 | K100: 0 | L100: 0 | M100: 0 | N100: 0 | O100: 0 | P100: 300.3 | Q100: 0 | R100: 0 | S100: 0 | T100: 300.3 | U100: 0 | V100: 0 | W100: 0 | X100: 0 | Y100: 0 | AD100: 0 | AE100: 0 | AF100: -89.32 | AG100: 0 | AH100: 0 | AI100: 0 | AJ100: 20981.27 | AK100: 0 | AL100: 0 | AM100: 0 | AN100: 0 | AO100: 0 | AP100: 20891.95
A101: 合计 | B101: 0 | C101: 0 | D101: 0 | E101: 0 | F101: 0 | G101: 0 | K101: 0 | L101: 0 | M101: 0 | N101: 0 | O101: 189.645 | P101: 416.61654 | Q101: 79009.244 | R101: 0 | S101: 0 | T101: - | U101: 0 | V101: 0 | W101: 0 | X101: - | Y101: 0 | Z101: 0 | AA101: - | AB101: 0 | AC101: 0 | AD101: 0 | AE101: 0 | AF101: -89.32 | AG101: 0 | AH101: 0 | AI101: 0 | AJ101: 20981.27 | AK101: 0 | AL101: 0 | AM101: 0 | AN101: 0 | AO101: 189.645 | AP101: 99901.194
